rgb_control/__init__.py
rgb_control/device.py
rgb_control/main.py
rgb_control/rgb_utils.py
rgb_control-0.0.1.dist-info/LICENSE
rgb_control-0.0.1.dist-info/METADATA
rgb_control-0.0.1.dist-info/WHEEL
rgb_control-0.0.1.dist-info/entry_points.txt
rgb_control-0.0.1.dist-info/top_level.txt
rgb_control-0.0.1.dist-info/RECORD
