Metadata-Version: 2.1
Name: rgb-control
Version: 0.0.1
Summary: The script allows you to set the RGB backlight color on A4Tech Bloody keyboards.
Home-page: https://github.com/apo5tol/bloody_keyboard_rgb_control
Author: Alexandr Kuzhel
Author-email: alexkuzhel.biz@gmail.com
License: UNKNOWN
Platform: UNKNOWN
Classifier: Programming Language :: Python :: 3
Classifier: License :: OSI Approved :: MIT License
Classifier: Operating System :: POSIX :: Linux
Requires-Python: >=3.6
Requires-Dist: pyusb (==1.1.0)
